meilisearch_status_check_decorator/__init__.py
meilisearch_status_check_decorator/py.typed
meilisearch_status_check_decorator-0.1.3.dist-info/LICENSE
meilisearch_status_check_decorator-0.1.3.dist-info/WHEEL
meilisearch_status_check_decorator-0.1.3.dist-info/METADATA
meilisearch_status_check_decorator-0.1.3.dist-info/RECORD
