Metadata-Version: 2.1
Name: meilisearch-status-check-decorator
Version: 0.1.3
Summary: A decorator to check for indexing status errors
Home-page: https://github.com/sanders41/meilisearch-status-check-decorator
License: MIT
Keywords: meilisearch,python,decorator
Author: Paul Sanders
Author-email: psanders1@gmail.com
Requires-Python: >=3.7,<4.0
Classifier: License :: OSI Approved :: MIT License
Classifier: Programming Language :: Python :: 3
Classifier: Programming Language :: Python :: 3.10
Classifier: Programming Language :: Python :: 3.7
Classifier: Programming Language :: Python :: 3.8
Classifier: Programming Language :: Python :: 3.9
Requires-Dist: meilisearch (>=0.16.0,<0.17.0)
Project-URL: Documentation, https://github.com/sanders41/meilisearch-status-check-decorator
Project-URL: Repository, https://github.com/sanders41/meilisearch-status-check-decorator
